celery_pulse/__init__.py
celery_pulse/beat.py
celery_pulse/bootstep.py
celery_pulse/executors.py
celery_pulse/utils.py
celery_pulse-0.0.4.dist-info/licenses/LICENSE
celery_pulse-0.0.4.dist-info/METADATA
celery_pulse-0.0.4.dist-info/WHEEL
celery_pulse-0.0.4.dist-info/top_level.txt
celery_pulse-0.0.4.dist-info/RECORD
