Metadata-Version: 2.4
Name: celery-pulse
Version: 0.0.4
Summary: A simple, framework-agnostic Celery health check mechanism using a heartbeat file.
Author-email: Kulbarakov Bakdoolot <kulbarakovbh@gmail.com>
License: MIT License
Keywords: celery,healthcheck,monitoring,heartbeat,django,flask,fastapi
Classifier: Development Status :: 4 - Beta
Classifier: Framework :: Celery
Classifier: Framework :: Django
Classifier: Framework :: Flask
Classifier: Intended Audience :: Developers
Classifier: License :: OSI Approved :: MIT License
Classifier: Programming Language :: Python :: 3
Classifier: Programming Language :: Python :: 3.9
Classifier: Programming Language :: Python :: 3.10
Classifier: Programming Language :: Python :: 3.11
Classifier: Programming Language :: Python :: 3.12
Classifier: Operating System :: OS Independent
Classifier: Topic :: System :: Monitoring
Requires-Python: >=3.9
License-File: LICENSE
Requires-Dist: celery>=5.0
Provides-Extra: gevent
Requires-Dist: gevent; extra == "gevent"
Dynamic: license-file
